hestia_earth/models/__init__.py
hestia_earth/models/cache_nodes.py
hestia_earth/models/cache_sites.py
hestia_earth/models/log.py
hestia_earth/models/preload_requests.py
hestia_earth/models/requirements.py
hestia_earth/models/version.py
hestia_earth/models/agribalyse2016/__init__.py
hestia_earth/models/agribalyse2016/fuelElectricity.py
hestia_earth/models/agribalyse2016/machineryInfrastructureDepreciatedAmountPerCycle.py
hestia_earth/models/akagiEtAl2011/__init__.py
hestia_earth/models/akagiEtAl2011/ch4ToAirCropResidueBurning.py
hestia_earth/models/akagiEtAl2011/nh3ToAirCropResidueBurning.py
hestia_earth/models/akagiEtAl2011/noxToAirCropResidueBurning.py
hestia_earth/models/akagiEtAl2011/pm25ToAirCropResidueBurning.py
hestia_earth/models/akagiEtAl2011/so2ToAirCropResidueBurning.py
hestia_earth/models/akagiEtAl2011/utils.py
hestia_earth/models/aware/__init__.py
hestia_earth/models/aware/scarcityWeightedWaterUse.py
hestia_earth/models/aware2_0/__init__.py
hestia_earth/models/aware2_0/scarcityWeightedWaterUse.py
hestia_earth/models/bafu2025/__init__.py
hestia_earth/models/bafu2025/cycle.py
hestia_earth/models/bafu2025/impact_assessment.py
hestia_earth/models/bafu2025/utils.py
hestia_earth/models/chaudharyBrooks2018/__init__.py
hestia_earth/models/chaudharyBrooks2018/damageToTerrestrialEcosystemsLandOccupation.py
hestia_earth/models/chaudharyBrooks2018/damageToTerrestrialEcosystemsLandTransformation.py
hestia_earth/models/chaudharyBrooks2018/damageToTerrestrialEcosystemsTotalLandUseEffects.py
hestia_earth/models/chaudharyBrooks2018/utils.py
hestia_earth/models/cml2001Baseline/__init__.py
hestia_earth/models/cml2001Baseline/abioticResourceDepletionFossilFuels.py
hestia_earth/models/cml2001Baseline/abioticResourceDepletionMineralsAndMetals.py
hestia_earth/models/cml2001Baseline/eutrophicationPotentialExcludingFate.py
hestia_earth/models/cml2001Baseline/resourceUseEnergyDepletionDuringCycle.py
hestia_earth_models-0.76.2.dist-info/licenses/LICENSE
hestia_earth_models-0.76.2.dist-info/METADATA
hestia_earth_models-0.76.2.dist-info/WHEEL
hestia_earth_models-0.76.2.dist-info/top_level.txt
hestia_earth_models-0.76.2.dist-info/RECORD
