Metadata-Version: 2.4
Name: hestia_earth_models
Version: 0.76.2
Summary: HESTIA's set of modules for filling gaps in the activity data using external datasets (e.g. populating soil properties with a geospatial dataset using provided coordinates) and internal lookups (e.g. populating machinery use from fuel use). Includes rules for when gaps should be filled versus not (e.g. never gap fill yield, gap fill crop residue if yield provided etc.).
Home-page: https://gitlab.com/hestia-earth/hestia-engine-models
Author: HESTIA Team
Author-email: guillaumeroyer.mail@gmail.com
License: MIT
Classifier: Programming Language :: Python :: 3.12
Requires-Python: >=3.12
License-File: LICENSE
Requires-Dist: hestia-earth-schema<36.0.0,>=35.3.0
Requires-Dist: hestia-earth-utils>=0.16.16
Requires-Dist: CurrencyConverter==0.16.8
Requires-Dist: haversine>=2.7.0
Requires-Dist: pydash
Requires-Dist: area
Provides-Extra: spatial
Requires-Dist: hestia-earth-earth-engine>=0.6.0; extra == "spatial"
Dynamic: author
Dynamic: author-email
Dynamic: classifier
Dynamic: description
Dynamic: description-content-type
Dynamic: home-page
Dynamic: license
Dynamic: license-file
Dynamic: provides-extra
Dynamic: requires-dist
Dynamic: requires-python
Dynamic: summary
